linalgebra/__init__.py
linalgebra/matrix.py
linalgebra/vector2.py
linalgebra/vector3.py
linalgebra/extras/__init__.py
linalgebra/extras/angles.py
linalgebra-0.2.0.dist-info/LICENSE
linalgebra-0.2.0.dist-info/METADATA
linalgebra-0.2.0.dist-info/WHEEL
linalgebra-0.2.0.dist-info/top_level.txt
linalgebra-0.2.0.dist-info/RECORD
