Metadata-Version: 2.1
Name: linalgebra
Version: 0.2.0
Summary: Linear algebra tools
Home-page: UNKNOWN
Author: Matthew G. Flegg
Author-email: <matthewflegg@outlook.com>
License: UNKNOWN
Keywords: python,package
Platform: UNKNOWN
Classifier: Development Status :: 3 - Alpha
Classifier: Intended Audience :: Education
Classifier: Programming Language :: Python :: 3
Classifier: Operating System :: Microsoft :: Windows
Classifier: Operating System :: MacOS :: MacOS X
License-File: LICENSE
